[
    {
        "name": "合众",
        "desc": "合众地区",
        "places": [
            {
                "name": "鹿子镇",
                "desc": "各种各样点子汇集的城鎮。",
                "points": 0,
                "npc": [
                    "pkm_center"
                ],
                "pkms": []
            },
            {
                "name": "１号道路",
                "desc": "难得的相遇，和大家说说话吧！\n他们肯定能告诉你一些有用的情报！",
                "points": 3,
                "pkms": [
                    {
                        "id": 1,
                        "chance": 1.0
                    }
                ]
            }
        ],
        "connect": [
            {
                "from": 0,
                "to": 1
            }
        ]
    }
]